{
  "doc_id": "circuit_doc_017",
  "file_name": "Week 7 Lecture 1 - Nature Response of a Parallel RLC Circuit.pdf",
  "group": "circuit_analysis",
  "questions": [
    {
      "category": "lecture_scope",
      "question": "这份讲义主要讲解了哪些核心概念、定律或电路类型？",
      "answer": ""
    },
    {
      "category": "worked_example",
      "question": "讲义中最典型的例题或代表性电路是什么，它要解决什么问题？",
      "answer": ""
    },
    {
      "category": "study_focus",
      "question": "如果我要快速复习这份讲义，最应该优先关注哪些公式、图示、结论或分析步骤？",
      "answer": ""
    },
    {
      "category": "known_unknown",
      "question": "该讲义例题中已知条件、待求量和使用的方法分别是什么？",
      "answer": ""
    },
    {
      "category": "method_selection",
      "question": "如果把这道题当成一次作业题，应该优先选择哪种分析方法，为什么？",
      "answer": ""
    },
    {
      "category": "equation_setup",
      "question": "文档中的关键方程是如何根据 KCL、KVL、元件关系或等效变换一步步建立起来的？",
      "answer": ""
    },
    {
      "category": "equivalent_transformation",
      "question": "如果文档涉及等效变换，原电路与等效电路之间是如何对应的？",
      "answer": ""
    },
    {
      "category": "solution_steps",
      "question": "该讲义中的典型电路题目是按什么步骤完成求解的？",
      "answer": ""
    },
    {
      "category": "result_interpretation",
      "question": "最终求得的电压、电流、功率或响应结果说明了什么电路特性？",
      "answer": ""
    },
    {
      "category": "rlc_response",
      "question": "该 RLC 电路对应的是自然响应还是受迫响应，其阻尼状态如何判断？",
      "answer": ""
    }
  ]
}